pb_process_tools-1.4.0.data/data/share/pbprocesstools/loggingconfig.json
pb_process_tools-1.4.0.data/scripts/genslurmsub.py
pb_process_tools-1.4.0.data/scripts/prefixcmdslst.py
pb_process_tools-1.4.0.data/scripts/splitcmdslist.py
pb_process_tools-1.4.0.data/scripts/subcmdslurm.py
pbprocesstools/__init__.py
pbprocesstools/pbpt_process.py
pbprocesstools/pbpt_q_process.py
pbprocesstools/pbpt_sbatch.py
pbprocesstools/pbpt_utils.py
pbprocesstools/templates/sbatchsub_basic.jinja2
pbprocesstools/templates/sbatchsub_basic_email.jinja2
pbprocesstools/templates/sbatchsub_basic_nnodes.jinja2
pbprocesstools/templates/sbatchsub_basic_nnodes_email.jinja2
pbprocesstools/templates/sbatchsub_gnuparallel.jinja2
pbprocesstools/templates/sbatchsub_gnuparallel_email.jinja2
pbprocesstools/templates/sbatchsub_gnuparallel_nnodes.jinja2
pbprocesstools/templates/sbatchsub_gnuparallel_nnodes_email.jinja2
pb_process_tools-1.4.0.dist-info/LICENSE.txt
pb_process_tools-1.4.0.dist-info/METADATA
pb_process_tools-1.4.0.dist-info/WHEEL
pb_process_tools-1.4.0.dist-info/top_level.txt
pb_process_tools-1.4.0.dist-info/RECORD
