Metadata-Version: 2.1
Name: pb-process-tools
Version: 1.4.0
Summary: Tools for batch processing data, including on HPC cluster with slurm.
Home-page: https://bitbucket.org/petebunting/pb_process_tools
Author: Pete Bunting
Author-email: petebunting@mac.com
License: LICENSE.txt
Platform: UNKNOWN
Classifier: Intended Audience :: Developers
Classifier: Operating System :: OS Independent
Classifier: Programming Language :: Python :: 3
Classifier: Programming Language :: Python :: 3.2
Classifier: Programming Language :: Python :: 3.3
Classifier: Programming Language :: Python :: 3.4
Classifier: Programming Language :: Python :: 3.5
Classifier: Programming Language :: Python :: 3.6
Classifier: Programming Language :: Python :: 3.7
Classifier: Programming Language :: Python :: 3.8
Requires-Dist: jinja2
Requires-Dist: sqlalchemy
Requires-Dist: tqdm
